{
  "additionalProperties": false,
  "properties": {
    "kind": {
      "default": "Tag",
      "description": "Tag displays a small categorical label",
      "type": "string"
    },
    "spec": {
      "additionalProperties": false,
      "properties": {
        "apiRef": {
          "additionalProperties": false,
          "properties": {
            "name": {
              "type": "string"
            },
            "namespace": {
              "type": "string"
            }
          },
          "required": [
            "name",
            "namespace"
          ],
          "type": "object"
        },
        "widgetData": {
          "additionalProperties": false,
          "type": "object",
          "required": [
            "label"
          ],
          "properties": {
            "label": {
              "description": "the tag text",
              "type": "string"
            },
            "color": {
              "description": "the tag color (preset name or hex)",
              "type": "string"
            },
            "bordered": {
              "description": "whether the tag has a border",
              "type": "boolean"
            }
          }
        },
        "widgetDataTemplate": {
          "items": {
            "additionalProperties": false,
            "properties": {
              "expression": {
                "type": "string"
              },
              "forPath": {
                "type": "string"
              }
            },
            "type": "object"
          },
          "type": "array"
        }
      },
      "required": [
        "widgetData"
      ],
      "type": "object"
    },
    "version": {
      "default": "v1beta1",
      "type": "string"
    }
  },
  "required": [
    "kind",
    "spec",
    "version"
  ],
  "type": "object"
}
